wirepusher_official/__init__.py
wirepusher_official/async_client.py
wirepusher_official/client.py
wirepusher_official/crypto.py
wirepusher_official/exceptions.py
wirepusher_official/models.py
wirepusher_official/py.typed
wirepusher_official/validation.py
wirepusher_official-1.0.0a6.dist-info/licenses/LICENSE
wirepusher_official-1.0.0a6.dist-info/METADATA
wirepusher_official-1.0.0a6.dist-info/WHEEL
wirepusher_official-1.0.0a6.dist-info/top_level.txt
wirepusher_official-1.0.0a6.dist-info/RECORD
