Metadata-Version: 2.4
Name: wirepusher_official
Version: 1.0.0a6
Summary: Official WirePusher client library for Python
Author-email: WirePusher <support@wirepusher.com>
License-Expression: MIT
Project-URL: Homepage, https://gitlab.com/wirepusher/python-sdk
Project-URL: Documentation, https://gitlab.com/wirepusher/python-sdk/-/blob/main/README.md
Project-URL: Repository, https://gitlab.com/wirepusher/python-sdk
Project-URL: Issues, https://gitlab.com/wirepusher/python-sdk/-/issues
Classifier: Development Status :: 4 - Beta
Classifier: Intended Audience :: Developers
Classifier: Programming Language :: Python :: 3
Classifier: Programming Language :: Python :: 3.9
Classifier: Programming Language :: Python :: 3.10
Classifier: Programming Language :: Python :: 3.11
Classifier: Programming Language :: Python :: 3.12
Classifier: Programming Language :: Python :: 3.13
Classifier: Topic :: Software Development :: Libraries :: Python Modules
Requires-Python: >=3.9
License-File: LICENSE
Requires-Dist: httpx>=0.24.0
Requires-Dist: cryptography>=41.0.0
Provides-Extra: dev
Requires-Dist: pytest>=7.0.0; extra == "dev"
Requires-Dist: pytest-asyncio>=0.21.0; extra == "dev"
Requires-Dist: pytest-cov>=4.0.0; extra == "dev"
Requires-Dist: pytest-httpx>=0.22.0; extra == "dev"
Requires-Dist: mypy>=1.0.0; extra == "dev"
Requires-Dist: black>=23.0.0; extra == "dev"
Requires-Dist: ruff>=0.1.0; extra == "dev"
Requires-Dist: pre-commit>=3.5.0; extra == "dev"
Dynamic: license-file
